yagpt_py/__init__.py
yagpt_py/authData.py
yagpt_py/messages.py
yagpt_py/response.py
yagpt_py-0.0.5.dist-info/METADATA
yagpt_py-0.0.5.dist-info/WHEEL
yagpt_py-0.0.5.dist-info/top_level.txt
yagpt_py-0.0.5.dist-info/RECORD
