Metadata-Version: 2.1
Name: yagpt_py
Version: 0.0.5
Summary: alpha version of YandexGPT package for Python.
Home-page: https://github.com/Misfit-s/yagpt_py
Author: Danila Suravenkov
Author-email: keepwannadie@gmail.com
Project-URL: GitHub, https://github.com/Misfit-s/yagpt_py
Keywords: Yandex API AI GPT language model
Classifier: Programming Language :: Python :: 3.12
Classifier: License :: OSI Approved :: MIT License
Classifier: Operating System :: OS Independent
Requires-Python: >=3.6
Requires-Dist: requests >=2.25.1
